Metadata-Version: 1.0
Name: micropython-upip
Version: 1.1
Summary: Simple package manager for MicroPython.
Home-page: https://github.com/micropython/micropython/issues/405
Author: MicroPython Developers
Author-email: micro-python@googlegroups.com
License: MIT
Platform: UNKNOWN
